{"code":1,"msg":"数据列表","page":1,"pagecount":5180,"limit":"20","total":103585,"list":[{"vod_id":110635,"vod_name":"龙世纪OVA","type_id":25,"type_name":"日本动漫","vod_en":"longshijiOVA","vod_time":"2026-05-12 22:26:02","vod_remarks":"第2集完结","vod_play_from":"jinyingyun,jinyingm3u8","vod_play_url":""},{"vod_id":107699,"vod_name":"身为悲剧始作俑者的最强邪恶BOSS女王为民竭心尽力第二季","type_id":25,"type_name":"日本动漫","vod_en":"shenweibeijushizuoyongzhedezuiqiangxieeBOSSnvwangweiminjiexinjinlidierji","vod_time":"2026-05-12 22:24:02","vod_remarks":"第6集","vod_play_from":"jinyingyun,jinyingm3u8","vod_play_url":""},{"vod_id":110640,"vod_name":"穿越神医，拯救短剧世界","type_id":30,"type_name":"短剧","vod_en":"chuanyueshenyizhengjiuduanjushijie","vod_time":"2026-05-12 22:12:02","vod_remarks":"全集完结","vod_play_from":"jinyingyun,jinyingm3u8","vod_play_url":""},{"vod_id":110639,"vod_name":"七零年代我靠巴掌改命","type_id":30,"type_name":"短剧","vod_en":"qilingniandaiwokaobazhanggaiming","vod_time":"2026-05-12 22:10:03","vod_remarks":"全集完结","vod_play_from":"jinyingyun,jinyingm3u8","vod_play_url":""},{"vod_id":110638,"vod_name":"裁员返乡遇神泉，女神倒追三条街","type_id":30,"type_name":"短剧","vod_en":"caiyuanfanxiangyushenquannvshendaozhuisantiaojie","vod_time":"2026-05-12 22:04:02","vod_remarks":"全集完结","vod_play_from":"jinyingyun,jinyingm3u8","vod_play_url":""},{"vod_id":107697,"vod_name":"百鬼夜行抄","type_id":25,"type_name":"日本动漫","vod_en":"baiguiyexingchao","vod_time":"2026-05-12 22:00:03","vod_remarks":"第6集","vod_play_from":"jinyingyun,jinyingm3u8","vod_play_url":""},{"vod_id":110637,"vod_name":"错爱一场风月","type_id":30,"type_name":"短剧","vod_en":"cuoaiyichangfengyue","vod_time":"2026-05-12 21:58:02","vod_remarks":"全集完结","vod_play_from":"jinyingyun,jinyingm3u8","vod_play_url":""},{"vod_id":110636,"vod_name":"穿回78：爆改混子，宠妻女带飞全村","type_id":30,"type_name":"短剧","vod_en":"chuanhui78baogaihunzichongqinvdaifeiquancun","vod_time":"2026-05-12 21:54:02","vod_remarks":"全集完结","vod_play_from":"jinyingyun,jinyingm3u8","vod_play_url":""},{"vod_id":94914,"vod_name":"失忆医生第二季","type_id":3,"type_name":"欧美剧","vod_en":"shiyiyishengdierji","vod_time":"2026-05-12 21:12:03","vod_remarks":"第18集","vod_play_from":"jinyingyun,jinyingm3u8","vod_play_url":""},{"vod_id":86721,"vod_name":"法律与秩序：特殊受害者 第二十七季","type_id":3,"type_name":"欧美剧","vod_en":"falvyuzhixuteshushouhaizhediershiqiji","vod_time":"2026-05-12 20:56:04","vod_remarks":"第20集","vod_play_from":"jinyingyun,jinyingm3u8","vod_play_url":""},{"vod_id":110634,"vod_name":"满级金钟罩，反派才是真大腿","type_id":30,"type_name":"短剧","vod_en":"manjijinzhongzhaofanpaicaishizhendatui","vod_time":"2026-05-12 20:36:03","vod_remarks":"全集完结","vod_play_from":"jinyingyun,jinyingm3u8","vod_play_url":""},{"vod_id":110633,"vod_name":"赝品新娘","type_id":30,"type_name":"短剧","vod_en":"yanpinxinniang","vod_time":"2026-05-12 20:28:02","vod_remarks":"全集完结","vod_play_from":"jinyingyun,jinyingm3u8","vod_play_url":""},{"vod_id":110632,"vod_name":"父兄战死只剩我，可我是纨绔啊","type_id":30,"type_name":"短剧","vod_en":"fuxiongzhansizhishengwokewoshiwankua","vod_time":"2026-05-12 20:26:03","vod_remarks":"全集完结","vod_play_from":"jinyingyun,jinyingm3u8","vod_play_url":""},{"vod_id":109577,"vod_name":"爱情没有神话","type_id":20,"type_name":"内地剧","vod_en":"aiqingmeiyoushenhua","vod_time":"2026-05-12 20:24:02","vod_remarks":"第32集","vod_play_from":"jinyingyun,jinyingm3u8","vod_play_url":""},{"vod_id":110631,"vod_name":"别横了，她掌天命","type_id":30,"type_name":"短剧","vod_en":"biehengliaotazhangtianming","vod_time":"2026-05-12 20:10:03","vod_remarks":"全集完结","vod_play_from":"jinyingyun,jinyingm3u8","vod_play_url":""},{"vod_id":110630,"vod_name":"师姐如云：我靠作死成大帝","type_id":30,"type_name":"短剧","vod_en":"shijieruyunwokaozuosichengdadi","vod_time":"2026-05-12 20:00:03","vod_remarks":"全集完结","vod_play_from":"jinyingyun,jinyingm3u8","vod_play_url":""},{"vod_id":110604,"vod_name":"贪吃姐弟","type_id":24,"type_name":"中国动漫","vod_en":"tanchijiedi","vod_time":"2026-05-12 19:58:04","vod_remarks":"第37集","vod_play_from":"jinyingyun,jinyingm3u8","vod_play_url":""},{"vod_id":110629,"vod_name":"我是全村第一个修仙的，必须卷","type_id":30,"type_name":"短剧","vod_en":"woshiquancundiyigexiuxiandebixujuan","vod_time":"2026-05-12 19:56:03","vod_remarks":"全集完结","vod_play_from":"jinyingyun,jinyingm3u8","vod_play_url":""},{"vod_id":110628,"vod_name":"霏霏向暖","type_id":30,"type_name":"短剧","vod_en":"feifeixiangnuan","vod_time":"2026-05-12 19:54:03","vod_remarks":"全集完结","vod_play_from":"jinyingyun,jinyingm3u8","vod_play_url":""},{"vod_id":110469,"vod_name":"主角","type_id":20,"type_name":"内地剧","vod_en":"zhujiao","vod_time":"2026-05-12 19:54:03","vod_remarks":"第7集","vod_play_from":"jinyingyun,jinyingm3u8","vod_play_url":""}],"class":[{"type_id":1,"type_pid":0,"type_name":"电视剧"},{"type_id":2,"type_pid":0,"type_name":"电影"},{"type_id":3,"type_pid":1,"type_name":"欧美剧"},{"type_id":4,"type_pid":1,"type_name":"香港剧"},{"type_id":5,"type_pid":1,"type_name":"韩剧"},{"type_id":6,"type_pid":1,"type_name":"日剧"},{"type_id":7,"type_pid":1,"type_name":"马泰剧"},{"type_id":8,"type_pid":0,"type_name":"伦理片"},{"type_id":9,"type_pid":2,"type_name":"动作片"},{"type_id":10,"type_pid":2,"type_name":"爱情片"},{"type_id":11,"type_pid":2,"type_name":"喜剧片"},{"type_id":12,"type_pid":2,"type_name":"科幻片"},{"type_id":13,"type_pid":2,"type_name":"恐怖片"},{"type_id":14,"type_pid":2,"type_name":"剧情片"},{"type_id":15,"type_pid":2,"type_name":"战争片"},{"type_id":16,"type_pid":2,"type_name":"记录片"},{"type_id":17,"type_pid":0,"type_name":"动漫"},{"type_id":20,"type_pid":1,"type_name":"内地剧"},{"type_id":23,"type_pid":2,"type_name":"动画片"},{"type_id":24,"type_pid":17,"type_name":"中国动漫"},{"type_id":25,"type_pid":17,"type_name":"日本动漫"},{"type_id":26,"type_pid":17,"type_name":"欧美动漫"},{"type_id":27,"type_pid":0,"type_name":"综艺"},{"type_id":28,"type_pid":1,"type_name":"台湾剧"},{"type_id":29,"type_pid":0,"type_name":"体育赛事"},{"type_id":30,"type_pid":0,"type_name":"短剧"},{"type_id":31,"type_pid":0,"type_name":"预告片"},{"type_id":32,"type_pid":29,"type_name":"足球"},{"type_id":33,"type_pid":29,"type_name":"篮球"},{"type_id":34,"type_pid":29,"type_name":"台球"},{"type_id":35,"type_pid":29,"type_name":"其他赛事"}]}
